<Index><File path="D:\dev.nicu\poo\BasicProgram\BasicProgram\RegistruAnimale.cpp" id="2" stamp="1578612010"  exclude="false"/><File path="D:\dev.nicu\poo\BasicProgram\BasicProgram\RegistruAnimale.h" id="1" stamp="1578611972"  exclude="false" include="true" bind="true"/><File path="D:\CppDepend\DefaultToolchain\compiler\include\c++\vector" id="6" stamp="1547491262"  exclude="false"/><File path="D:\CppDepend\DefaultToolchain\compiler\include\c++\bits\stl_algobase.h" id="7" stamp="1547491258"  exclude="false"/><File path="D:\CppDepend\DefaultToolchain\compiler\include\c++\mingw32\bits\c++config.h" id="8" stamp="1547491262"  exclude="false"/><File path="D:\CppDepend\DefaultToolchain\compiler\include\c++\mingw32\bits\os_defines.h" id="9" stamp="1547491262"  exclude="false"/><File path="D:\CppDepend\DefaultToolchain\compiler\include\c++\mingw32\bits\cpu_defines.h" id="10" stamp="1547491262"  exclude="false"/><File path="D:\CppDepend\DefaultToolchain\compiler\include\c++\bits\functexcept.h" id="11" stamp="1547491258"  exclude="false"/><File path="D:\CppDepend\DefaultToolchain\compiler\include\c++\bits\exception_defines.h" id="12" stamp="1547491264"  exclude="false"/><File path="D:\CppDepend\DefaultToolchain\compiler\include\c++\bits\cpp_type_traits.h" id="13" stamp="1547491258"  exclude="false"/><File path="D:\CppDepend\DefaultToolchain\compiler\include\c++\ext\type_traits.h" id="14" stamp="1547491258"  exclude="false"/><File path="D:\CppDepend\DefaultToolchain\compiler\include\c++\ext\numeric_traits.h" id="15" stamp="1547491258"  exclude="false"/><File path="D:\CppDepend\DefaultToolchain\compiler\include\c++\bits\stl_pair.h" id="16" stamp="1547491258"  exclude="false"/><File path="D:\CppDepend\DefaultToolchain\compiler\include\c++\bits\move.h" id="17" stamp="1547491258"  exclude="false"/><File path="D:\CppDepend\DefaultToolchain\compiler\include\c++\bits\concept_check.h" id="18" stamp="1547491258"  exclude="false"/><File path="D:\CppDepend\DefaultToolchain\compiler\include\c++\type_traits" id="19" stamp="1547491262"  exclude="false"/><File path="D:\CppDepend\DefaultToolchain\compiler\include\c++\bits\stl_iterator_base_types.h" id="20" stamp="1547491258"  exclude="false"/><File path="D:\CppDepend\DefaultToolchain\compiler\include\c++\bits\stl_iterator_base_funcs.h" id="21" stamp="1547491258"  exclude="false"/><File path="D:\CppDepend\DefaultToolchain\compiler\include\c++\debug\assertions.h" id="22" stamp="1547491262"  exclude="false"/><File path="D:\CppDepend\DefaultToolchain\compiler\include\c++\bits\stl_iterator.h" id="23" stamp="1547491258"  exclude="false"/><File path="D:\CppDepend\DefaultToolchain\compiler\include\c++\bits\ptr_traits.h" id="24" stamp="1547491258"  exclude="false"/><File path="D:\CppDepend\DefaultToolchain\compiler\include\c++\debug\debug.h" id="25" stamp="1547491262"  exclude="false"/><File path="D:\CppDepend\DefaultToolchain\compiler\include\c++\bits\predefined_ops.h" id="26" stamp="1547491258"  exclude="false"/><File path="D:\CppDepend\DefaultToolchain\compiler\include\c++\bits\allocator.h" id="3" stamp="1547491258"  exclude="false"/><File path="D:\CppDepend\DefaultToolchain\compiler\include\c++\mingw32\bits\c++allocator.h" id="27" stamp="1547491262"  exclude="false"/><File path="D:\CppDepend\DefaultToolchain\compiler\include\c++\ext\new_allocator.h" id="28" stamp="1547491258"  exclude="false"/><File path="D:\CppDepend\DefaultToolchain\compiler\include\c++\new" id="29" stamp="1547491264"  exclude="false"/><File path="D:\CppDepend\DefaultToolchain\compiler\include\c++\exception" id="30" stamp="1547491264"  exclude="false"/><File path="D:\CppDepend\DefaultToolchain\compiler\include\c++\bits\exception.h" id="31" stamp="1547491264"  exclude="false"/><File path="D:\CppDepend\DefaultToolchain\compiler\include\c++\bits\exception_ptr.h" id="32" stamp="1547491264"  exclude="false"/><File path="D:\CppDepend\DefaultToolchain\compiler\include\c++\bits\cxxabi_init_exception.h" id="33" stamp="1547491264"  exclude="false"/><File path="D:\CppDepend\DefaultToolchain\compiler\include\stddef.h" id="34" stamp="1547488190"  exclude="false"/><File path="D:\CppDepend\DefaultToolchain\compiler\include\c++\typeinfo" id="35" stamp="1547491264"  exclude="false"/><File path="D:\CppDepend\DefaultToolchain\compiler\include\c++\bits\hash_bytes.h" id="36" stamp="1547491264"  exclude="false"/><File path="D:\CppDepend\DefaultToolchain\compiler\include\c++\bits\nested_exception.h" id="37" stamp="1547491264"  exclude="false"/><File path="D:\CppDepend\DefaultToolchain\compiler\include\c++\bits\memoryfwd.h" id="38" stamp="1547491258"  exclude="false"/><File path="D:\CppDepend\DefaultToolchain\compiler\include\c++\bits\stl_construct.h" id="39" stamp="1547491258"  exclude="false"/><File path="D:\CppDepend\DefaultToolchain\compiler\include\c++\ext\alloc_traits.h" id="40" stamp="1547491258"  exclude="false"/><File path="D:\CppDepend\DefaultToolchain\compiler\include\c++\bits\alloc_traits.h" id="41" stamp="1547491258"  exclude="false"/><File path="D:\CppDepend\DefaultToolchain\compiler\include\c++\bits\stl_uninitialized.h" id="42" stamp="1547491258"  exclude="false"/><File path="D:\CppDepend\DefaultToolchain\compiler\include\c++\utility" id="43" stamp="1547491262"  exclude="false"/><File path="D:\CppDepend\DefaultToolchain\compiler\include\c++\bits\stl_relops.h" id="44" stamp="1547491258"  exclude="false"/><File path="D:\CppDepend\DefaultToolchain\compiler\include\c++\initializer_list" id="45" stamp="1547491264"  exclude="false"/><File path="D:\CppDepend\DefaultToolchain\compiler\include\c++\bits\stl_vector.h" id="4" stamp="1547491258"  exclude="false"/><File path="D:\CppDepend\DefaultToolchain\compiler\include\c++\bits\stl_bvector.h" id="46" stamp="1547491258"  exclude="false"/><File path="D:\CppDepend\DefaultToolchain\compiler\include\c++\bits\functional_hash.h" id="47" stamp="1547491258"  exclude="false"/><File path="D:\CppDepend\DefaultToolchain\compiler\include\c++\bits\range_access.h" id="48" stamp="1547491258"  exclude="false"/><File path="D:\CppDepend\DefaultToolchain\compiler\include\c++\bits\vector.tcc" id="49" stamp="1547491258"  exclude="false"/><File path="D:\dev.nicu\poo\BasicProgram\BasicProgram\Animal.h" id="5" stamp="1606434968"  exclude="false"/><File path="D:\CppDepend\DefaultToolchain\compiler\include\c++\iostream" id="50" stamp="1547491262"  exclude="false"/><File path="D:\CppDepend\DefaultToolchain\compiler\include\c++\ostream" id="51" stamp="1547491262"  exclude="false"/><File path="D:\CppDepend\DefaultToolchain\compiler\include\c++\ios" id="52" stamp="1547491262"  exclude="false"/><File path="D:\CppDepend\DefaultToolchain\compiler\include\c++\iosfwd" id="53" stamp="1547491262"  exclude="false"/><File path="D:\CppDepend\DefaultToolchain\compiler\include\c++\bits\stringfwd.h" id="54" stamp="1547491258"  exclude="false"/><File path="D:\CppDepend\DefaultToolchain\compiler\include\c++\bits\postypes.h" id="55" stamp="1547491258"  exclude="false"/><File path="D:\CppDepend\DefaultToolchain\compiler\include\c++\cwchar" id="56" stamp="1547491262"  exclude="false"/><File path="D:\CppDepend\DefaultToolchain\include\wchar.h" id="57" stamp="1548162050"  exclude="false"/><File path="D:\CppDepend\DefaultToolchain\include\_mingw.h" id="58" stamp="1548162050"  exclude="false"/><File path="D:\CppDepend\DefaultToolchain\include\msvcrtver.h" id="59" stamp="1548162050"  exclude="false"/><File path="D:\CppDepend\DefaultToolchain\include\w32api.h" id="60" stamp="1548162064"  exclude="false"/><File path="D:\CppDepend\DefaultToolchain\include\sdkddkver.h" id="61" stamp="1548162064"  exclude="false"/><File path="D:\CppDepend\DefaultToolchain\include\features.h" id="62" stamp="1553702636"  exclude="false"/><File path="D:\CppDepend\DefaultToolchain\include\wctype.h" id="63" stamp="1548162050"  exclude="false"/><File path="D:\CppDepend\DefaultToolchain\include\sys\types.h" id="64" stamp="1548162050"  exclude="false"/><File path="D:\CppDepend\DefaultToolchain\include\stdio.h" id="65" stamp="1548162050"  exclude="false"/><File path="D:\CppDepend\DefaultToolchain\include\stdlib.h" id="66" stamp="1548162050"  exclude="false"/><File path="D:\CppDepend\DefaultToolchain\include\direct.h" id="67" stamp="1548162050"  exclude="false"/><File path="D:\CppDepend\DefaultToolchain\include\sys\stat.h" id="68" stamp="1548162050"  exclude="false"/><File path="D:\CppDepend\DefaultToolchain\include\conio.h" id="69" stamp="1548162050"  exclude="false"/><File path="D:\CppDepend\DefaultToolchain\include\io.h" id="70" stamp="1548162050"  exclude="false"/><File path="D:\CppDepend\DefaultToolchain\include\stdint.h" id="71" stamp="1548162050"  exclude="false"/><File path="D:\CppDepend\DefaultToolchain\include\time.h" id="72" stamp="1548162050"  exclude="false"/><File path="D:\CppDepend\DefaultToolchain\include\locale.h" id="73" stamp="1548162050"  exclude="false"/><File path="D:\CppDepend\DefaultToolchain\include\process.h" id="74" stamp="1548162050"  exclude="false"/><File path="D:\CppDepend\DefaultToolchain\compiler\include\c++\bits\char_traits.h" id="75" stamp="1547491258"  exclude="false"/><File path="D:\CppDepend\DefaultToolchain\compiler\include\c++\cstdint" id="76" stamp="1547491262"  exclude="false"/><File path="D:\CppDepend\DefaultToolchain\compiler\include\c++\bits\localefwd.h" id="77" stamp="1547491258"  exclude="false"/><File path="D:\CppDepend\DefaultToolchain\compiler\include\c++\mingw32\bits\c++locale.h" id="78" stamp="1547491262"  exclude="false"/><File path="D:\CppDepend\DefaultToolchain\compiler\include\c++\clocale" id="79" stamp="1547491262"  exclude="false"/><File path="D:\CppDepend\DefaultToolchain\compiler\include\c++\cctype" id="80" stamp="1547491262"  exclude="false"/><File path="D:\CppDepend\DefaultToolchain\include\ctype.h" id="81" stamp="1548162050"  exclude="false"/><File path="D:\CppDepend\DefaultToolchain\compiler\include\c++\bits\ios_base.h" id="82" stamp="1547491258"  exclude="false"/><File path="D:\CppDepend\DefaultToolchain\compiler\include\c++\ext\atomicity.h" id="83" stamp="1547491258"  exclude="false"/><File path="D:\CppDepend\DefaultToolchain\compiler\include\c++\mingw32\bits\gthr.h" id="84" stamp="1547491262"  exclude="false"/><File path="D:\CppDepend\DefaultToolchain\compiler\include\c++\mingw32\bits\gthr-default.h" id="85" stamp="1547491262"  exclude="false"/><File path="D:\CppDepend\DefaultToolchain\include\errno.h" id="86" stamp="1548162050"  exclude="false"/><File path="D:\CppDepend\DefaultToolchain\compiler\include\c++\mingw32\bits\atomic_word.h" id="87" stamp="1547491262"  exclude="false"/><File path="D:\CppDepend\DefaultToolchain\compiler\include\c++\bits\locale_classes.h" id="88" stamp="1547491258"  exclude="false"/><File path="D:\CppDepend\DefaultToolchain\compiler\include\c++\string" id="89" stamp="1547491262"  exclude="false"/><File path="D:\CppDepend\DefaultToolchain\compiler\include\c++\bits\ostream_insert.h" id="90" stamp="1547491258"  exclude="false"/><File path="D:\CppDepend\DefaultToolchain\compiler\include\c++\bits\cxxabi_forced.h" id="91" stamp="1547491264"  exclude="false"/><File path="D:\CppDepend\DefaultToolchain\compiler\include\c++\bits\stl_function.h" id="92" stamp="1547491258"  exclude="false"/><File path="D:\CppDepend\DefaultToolchain\compiler\include\c++\backward\binders.h" id="93" stamp="1547491258"  exclude="false"/><File path="D:\CppDepend\DefaultToolchain\compiler\include\c++\bits\basic_string.h" id="94" stamp="1547491258"  exclude="false"/><File path="D:\CppDepend\DefaultToolchain\compiler\include\c++\string_view" id="95" stamp="1547491262"  exclude="false"/><File path="D:\CppDepend\DefaultToolchain\compiler\include\c++\limits" id="96" stamp="1547491262"  exclude="false"/><File path="D:\CppDepend\DefaultToolchain\compiler\include\c++\bits\string_view.tcc" id="97" stamp="1547491258"  exclude="false"/><File path="D:\CppDepend\DefaultToolchain\compiler\include\c++\ext\string_conversions.h" id="98" stamp="1547491258"  exclude="false"/><File path="D:\CppDepend\DefaultToolchain\compiler\include\c++\cstdlib" id="99" stamp="1547491262"  exclude="false"/><File path="D:\CppDepend\DefaultToolchain\compiler\include\c++\tr1\stdlib.h" id="100" stamp="1547491262"  exclude="false"/><File path="D:\CppDepend\DefaultToolchain\compiler\include\c++\tr1\cstdlib" id="101" stamp="1547491262"  exclude="false"/><File path="D:\CppDepend\DefaultToolchain\compiler\include\c++\bits\std_abs.h" id="102" stamp="1547491258"  exclude="false"/><File path="D:\CppDepend\DefaultToolchain\compiler\include\c++\cstdio" id="103" stamp="1547491262"  exclude="false"/><File path="D:\CppDepend\DefaultToolchain\compiler\include\c++\cerrno" id="104" stamp="1547491262"  exclude="false"/><File path="D:\CppDepend\DefaultToolchain\compiler\include\c++\bits\basic_string.tcc" id="105" stamp="1547491258"  exclude="false"/><File path="D:\CppDepend\DefaultToolchain\compiler\include\c++\bits\locale_classes.tcc" id="106" stamp="1547491258"  exclude="false"/><File path="D:\CppDepend\DefaultToolchain\compiler\include\c++\system_error" id="107" stamp="1547491262"  exclude="false"/><File path="D:\CppDepend\DefaultToolchain\compiler\include\c++\mingw32\bits\error_constants.h" id="108" stamp="1547491262"  exclude="false"/><File path="D:\CppDepend\DefaultToolchain\compiler\include\c++\stdexcept" id="109" stamp="1547491262"  exclude="false"/><File path="D:\CppDepend\DefaultToolchain\compiler\include\c++\streambuf" id="110" stamp="1547491262"  exclude="false"/><File path="D:\CppDepend\DefaultToolchain\compiler\include\c++\bits\streambuf.tcc" id="111" stamp="1547491258"  exclude="false"/><File path="D:\CppDepend\DefaultToolchain\compiler\include\c++\bits\basic_ios.h" id="112" stamp="1547491258"  exclude="false"/><File path="D:\CppDepend\DefaultToolchain\compiler\include\c++\bits\locale_facets.h" id="113" stamp="1547491258"  exclude="false"/><File path="D:\CppDepend\DefaultToolchain\compiler\include\c++\cwctype" id="114" stamp="1547491262"  exclude="false"/><File path="D:\CppDepend\DefaultToolchain\compiler\include\c++\mingw32\bits\ctype_base.h" id="115" stamp="1547491262"  exclude="false"/><File path="D:\CppDepend\DefaultToolchain\compiler\include\c++\bits\streambuf_iterator.h" id="116" stamp="1547491258"  exclude="false"/><File path="D:\CppDepend\DefaultToolchain\compiler\include\c++\mingw32\bits\ctype_inline.h" id="117" stamp="1547491262"  exclude="false"/><File path="D:\CppDepend\DefaultToolchain\compiler\include\c++\bits\locale_facets.tcc" id="118" stamp="1547491258"  exclude="false"/><File path="D:\CppDepend\DefaultToolchain\compiler\include\c++\bits\basic_ios.tcc" id="119" stamp="1547491258"  exclude="false"/><File path="D:\CppDepend\DefaultToolchain\compiler\include\c++\bits\ostream.tcc" id="120" stamp="1547491258"  exclude="false"/><File path="D:\CppDepend\DefaultToolchain\compiler\include\c++\istream" id="121" stamp="1547491262"  exclude="false"/><File path="D:\CppDepend\DefaultToolchain\compiler\include\c++\bits\istream.tcc" id="122" stamp="1547491258"  exclude="false"/></Index>